{
   "type": "FeatureCollection",
   "name": "transit-usa",
   "features": [
       {
           "type": "Feature",
           "geometry": {
               "type": "Point",
               "coordinates": [
                   -73.994,
                   40.735
               ]
           },
           "properties": {
               "place_name": "New York, New York",
               "zoom": 12,
               "tags": {
                   "custom-icon": "false"
               },
               "highlights": [
                   {
                       "geometry_type": "Point",
                       "data_layer": "transit_stop_label",
                       "data_layer_fields": {
                           "mode": "rail"
                       }
                   }
               ]
           }
       },
       {
           "type": "Feature",
           "geometry": {
               "type": "Point",
               "coordinates": [
                   -73.994,
                   40.735
               ]
           },
           "properties": {
               "place_name": "New York, New York",
               "zoom": 13,
               "tags": {
                   "custom-icon": "true"
               },
               "highlights": [
                   {
                       "geometry_type": "Point",
                       "data_layer": "transit_stop_label",
                       "data_layer_fields": {
                           "mode": "metro_rail"
                       }
                   },
                   {
                       "geometry_type": "Point",
                       "data_layer": "transit_stop_label",
                       "data_layer_fields": {
                           "mode": "rail"
                       }
                   }
               ]
           }
       },
       {
           "type": "Feature",
           "geometry": {
               "type": "Point",
               "coordinates": [
                   -73.991,
                   40.745
               ]
           },
           "properties": {
               "place_name": "New York, New York",
               "zoom": 14,
               "tags": {
                   "custom-icon": "true"
               },
               "highlights": [
                   {
                       "geometry_type": "Point",
                       "data_layer": "transit_stop_label",
                       "data_layer_fields": {
                           "mode": "metro_rail"
                       }
                   },
                   {
                       "geometry_type": "Point",
                       "data_layer": "transit_stop_label",
                       "data_layer_fields": {
                           "mode": "rail"
                       }
                   }
               ]
           }
       },
       {
           "type": "Feature",
           "geometry": {
               "type": "Point",
               "coordinates": [
                   -74.012,
                   40.702
               ]
           },
           "properties": {
               "place_name": "New York, New York",
               "zoom": 15,
               "tags": {
                   "custom-icon": "true"
               },
               "highlights": [
                   {
                       "geometry_type": "Point",
                       "data_layer": "transit_stop_label",
                       "data_layer_fields": {
                           "mode": "ferry"
                       }
                   },
                   {
                       "geometry_type": "Point",
                       "data_layer": "transit_stop_label",
                       "data_layer_fields": {
                           "mode": "metro_rail"
                       }
                   }
               ]
           }
       },
       {
           "type": "Feature",
           "geometry": {
               "type": "Point",
               "coordinates": [
                   -74.012,
                   40.702
               ]
           },
           "properties": {
               "place_name": "New York, New York",
               "zoom": 16,
               "tags": {
                   "custom-icon": "true"
               },
               "highlights": [
                   {
                       "geometry_type": "Point",
                       "data_layer": "transit_stop_label",
                       "data_layer_fields": {
                           "mode": "ferry"
                       }
                   },
                   {
                       "geometry_type": "Point",
                       "data_layer": "transit_stop_label",
                       "data_layer_fields": {
                           "mode": "bicycle"
                       }
                   },
                   {
                       "geometry_type": "Point",
                       "data_layer": "transit_stop_label",
                       "data_layer_fields": {
                           "mode": "metro_rail"
                       }
                   }
               ]
           }
       },
       {
           "type": "Feature",
           "geometry": {
               "type": "Point",
               "coordinates": [
                   -73.991,
                   40.735
               ]
           },
           "properties": {
               "place_name": "New York, New York",
               "zoom": 17,
               "tags": {
                   "custom-icon": "true"
               },
               "highlights": [
                   {
                       "geometry_type": "Point",
                       "data_layer": "transit_stop_label",
                       "data_layer_fields": {
                           "mode": "bicycle"
                       }
                   },
                   {
                       "geometry_type": "Point",
                       "data_layer": "transit_stop_label",
                       "data_layer_fields": {
                           "mode": "bus"
                       }
                   },
                   {
                       "geometry_type": "Point",
                       "data_layer": "transit_stop_label",
                       "data_layer_fields": {
                           "mode": "metro_rail"
                       }
                   }
               ]
           }
       },
       {
           "type": "Feature",
           "geometry": {
               "type": "Point",
               "coordinates": [
                   -73.991,
                   40.735
               ]
           },
           "properties": {
               "place_name": "New York, New York",
               "zoom": 18,
               "description": "Bus and bikelabels appear.",
               "tags": {
                   "custom-icon": "true"
               },
               "highlights": [
                   {
                       "geometry_type": "Point",
                       "data_layer": "transit_stop_label",
                       "data_layer_fields": {
                           "mode": "bus"
                       }
                   },
                   {
                       "geometry_type": "Point",
                       "data_layer": "transit_stop_label",
                       "data_layer_fields": {
                           "mode": "bicycle"
                       }
                   },
                   {
                       "geometry_type": "Point",
                       "data_layer": "transit_stop_label",
                       "data_layer_fields": {
                           "mode": "metro_rail"
                       }
                   }
               ]
           }
       },
       {
           "type": "Feature",
           "geometry": {
               "type": "Point",
               "coordinates": [
                   -73.991,
                   40.735
               ]
           },
           "properties": {
               "place_name": "New York, New York",
               "zoom": 19,
               "tags": {
                   "custom-icon": "true"
               },
               "highlights": [
                   {
                       "geometry_type": "Point",
                       "data_layer": "transit_stop_label",
                       "data_layer_fields": {
                           "stop_type": "entrance"
                       }
                   }
               ]
           }
       },
       {
           "type": "Feature",
           "geometry": {
               "type": "Point",
               "coordinates": [
                   -77.018,
                   38.891
               ]
           },
           "properties": {
               "place_name": "Washington, DC",
               "zoom": 14,
               "tags": {
                   "custom-icon": "true"
               },
               "highlights": [
                   {
                       "geometry_type": "Point",
                       "data_layer": "transit_stop_label",
                       "data_layer_fields": {
                           "maki": "rail-metro"
                       }
                   },
                   {
                       "geometry_type": "Point",
                       "data_layer": "transit_stop_label",
                       "data_layer_fields": {
                           "mode": "rail"
                       }
                   }
               ]
           }
       },
       {
           "type": "Feature",
           "geometry": {
               "type": "Point",
               "coordinates": [
                   -77.006,
                   38.897
               ]
           },
           "properties": {
               "place_name": "Washington, DC",
               "zoom": 16,
               "tags": {
                   "custom-icon": "true"
               },
               "highlights": [
                   {
                       "geometry_type": "Point",
                       "data_layer": "transit_stop_label",
                       "data_layer_fields": {
                           "mode": "metro_rail"
                       }
                   },
                   {
                       "geometry_type": "Point",
                       "data_layer": "transit_stop_label",
                       "data_layer_fields": {
                           "mode": "rail"
                       }
                   },
                   {
                       "geometry_type": "Point",
                       "data_layer": "transit_stop_label",
                       "data_layer_fields": {
                           "mode": "bicycle"
                       }
                   }
               ]
           }
       },
       {
           "type": "Feature",
           "geometry": {
               "type": "Point",
               "coordinates": [
                   -122.404,
                   37.782
               ]
           },
           "properties": {
               "place_name": "San Francisco, California",
               "zoom": 14,
               "tags": {
                   "custom-icon": "true"
               },
               "highlights": [
                   {
                       "geometry_type": "Point",
                       "data_layer": "transit_stop_label",
                       "data_layer_fields": {
                           "mode": "metro_rail"
                       }
                   },
                   {
                       "geometry_type": "Point",
                       "data_layer": "transit_stop_label",
                       "data_layer_fields": {
                           "mode": "rail"
                       }
                   }
               ]
           }
       },
       {
           "type": "Feature",
           "geometry": {
               "type": "Point",
               "coordinates": [
                   -122.43,
                   37.767
               ]
           },
           "properties": {
               "place_name": "San Francisco, California",
               "zoom": 15,
               "tags": {
                   "custom-icon": "false"
               },
               "highlights": [
                   {
                       "geometry_type": "Point",
                       "data_layer": "transit_stop_label",
                       "data_layer_fields": {
                           "mode": "light_rail"
                       }
                   }
               ]
           }
       },
       {
           "type": "Feature",
           "geometry": {
               "type": "Point",
               "coordinates": [
                   -122.394,
                   37.796
               ]
           },
           "properties": {
               "place_name": "San Francisco, California",
               "zoom": 16,
               "tags": {
                   "custom-icon": "false"
               },
               "highlights": [
                   {
                       "geometry_type": "Point",
                       "data_layer": "transit_stop_label",
                       "data_layer_fields": {
                           "mode": "tram"
                       }
                   },
                   {
                       "geometry_type": "Point",
                       "data_layer": "transit_stop_label",
                       "data_layer_fields": {
                           "mode": "ferry"
                       }
                   },
                   {
                       "geometry_type": "Point",
                       "data_layer": "transit_stop_label",
                       "data_layer_fields": {
                           "mode": "bicycle"
                       }
                   }
               ]
           }
       },
       {
           "type": "Feature",
           "geometry": {
               "type": "Point",
               "coordinates": [
                   -75.164,
                   39.951
               ]
           },
           "properties": {
               "place_name": "Philadelphia, Pennsylvania",
               "zoom": 13,
               "tags": {
                   "custom-icon": "true"
               },
               "highlights": [
                   {
                       "geometry_type": "Point",
                       "data_layer": "transit_stop_label",
                       "data_layer_fields": {
                           "mode": "metro_rail"
                       }
                   }
               ]
           }
       },
       {
           "type": "Feature",
           "geometry": {
               "type": "Point",
               "coordinates": [
                   -75.164,
                   39.951
               ]
           },
           "properties": {
               "place_name": "Philadelphia, Pennsylvania",
               "zoom": 15,
               "tags": {
                   "custom-icon": "true"
               },
               "highlights": [
                   {
                       "geometry_type": "Point",
                       "data_layer": "transit_stop_label",
                       "data_layer_fields": {
                           "mode": "metro_rail"
                       }
                   }
               ]
           }
       },
       {
           "type": "Feature",
           "geometry": {
               "type": "Point",
               "coordinates": [
                   -75.164,
                   39.951
               ]
           },
           "properties": {
               "place_name": "Philadelphia, Pennsylvania",
               "zoom": 19,
               "tags": {
                   "custom-icon": "false"
               },
               "highlights": [
                   {
                       "geometry_type": "Point",
                       "data_layer": "transit_stop_label",
                       "data_layer_fields": {
                           "stop_type": "entrance"
                       }
                   },
                   {
                       "geometry_type": "Point",
                       "data_layer": "transit_stop_label",
                       "data_layer_fields": {
                           "mode": "metro_rail"
                       }
                   },
                   {
                       "geometry_type": "Point",
                       "data_layer": "transit_stop_label",
                       "data_layer_fields": {
                           "mode": "bus"
                       }
                   }
               ]
           }
       },
       {
           "type": "Feature",
           "geometry": {
               "type": "Point",
               "coordinates": [
                   -71.052,
                   42.359
               ]
           },
           "properties": {
               "place_name": "Boston, Massachusetts",
               "zoom": 13,
               "tags": {
                   "custom-icon": "true"
               },
               "highlights": [
                   {
                       "geometry_type": "Point",
                       "data_layer": "transit_stop_label",
                       "data_layer_fields": {
                           "mode": "metro_rail"
                       }
                   }
               ]
           }
       },
       {
           "type": "Feature",
           "geometry": {
               "type": "Point",
               "coordinates": [
                   -71.052,
                   42.359
               ]
           },
           "properties": {
               "place_name": "Boston, Massachusetts",
               "zoom": 16,
               "tags": {
                   "custom-icon": "true"
               },
               "highlights": [
                   {
                       "geometry_type": "Point",
                       "data_layer": "transit_stop_label",
                       "data_layer_fields": {
                           "mode": "bicycle"
                       }
                   },
                   {
                       "geometry_type": "Point",
                       "data_layer": "transit_stop_label",
                       "data_layer_fields": {
                           "mode": "ferry"
                       }
                   },
                   {
                       "geometry_type": "Point",
                       "data_layer": "transit_stop_label",
                       "data_layer_fields": {
                           "mode": "metro_rail"
                       }
                   }
               ]
           }
       },
       {
           "type": "Feature",
           "geometry": {
               "type": "Point",
               "coordinates": [
                   -71.052,
                   42.359
               ]
           },
           "properties": {
               "place_name": "Boston, Massachusetts",
               "zoom": 17,
               "tags": {
                   "custom-icon": "true"
               },
               "highlights": [
                   {
                       "geometry_type": "Point",
                       "data_layer": "transit_stop_label",
                       "data_layer_fields": {
                           "mode": "bus"
                       }
                   },
                   {
                       "geometry_type": "Point",
                       "data_layer": "transit_stop_label",
                       "data_layer_fields": {
                           "mode": "bicycle"
                       }
                   },
                   {
                       "geometry_type": "Point",
                       "data_layer": "transit_stop_label",
                       "data_layer_fields": {
                           "mode": "metro_rail"
                       }
                   },
                   {
                       "geometry_type": "Point",
                       "data_layer": "transit_stop_label",
                       "data_layer_fields": {
                           "mode": "ferry"
                       }
                   }
               ]
           }
       },
       {
           "type": "Feature",
           "geometry": {
               "type": "Point",
               "coordinates": [
                   -87.628,
                   41.878
               ]
           },
           "properties": {
               "place_name": "Chicago, Illinois",
               "zoom": 13,
               "tags": {
                   "custom-icon": "false"
               },
               "highlights": [
                   {
                       "geometry_type": "Point",
                       "data_layer": "transit_stop_label",
                       "data_layer_fields": {
                           "mode": "metro_rail"
                       }
                   },
                   {
                       "geometry_type": "Point",
                       "data_layer": "transit_stop_label",
                       "data_layer_fields": {
                           "mode": "rail"
                       }
                   }
               ]
           }
       },
       {
           "type": "Feature",
           "geometry": {
               "type": "Point",
               "coordinates": [
                   -87.628,
                   41.878
               ]
           },
           "properties": {
               "place_name": "Chicago, Illinois",
               "zoom": 17,
               "tags": {
                   "custom-icon": "false"
               },
               "highlights": [
                   {
                       "geometry_type": "Point",
                       "data_layer": "transit_stop_label",
                       "data_layer_fields": {
                           "mode": "metro_rail"
                       }
                   },
                   {
                       "geometry_type": "Point",
                       "data_layer": "transit_stop_label",
                       "data_layer_fields": {
                           "mode": "bus"
                       }
                   }
               ]
           }
       },
       {
           "type": "Feature",
           "geometry": {
               "type": "Point",
               "coordinates": [
                   -122.68,
                   45.516
               ]
           },
           "properties": {
               "place_name": "Portland, Oregon",
               "zoom": 17,
               "tags": {
                   "custom-icon": "false"
               },
               "highlights": [
                   {
                       "geometry_type": "Point",
                       "data_layer": "transit_stop_label",
                       "data_layer_fields": {
                           "mode": "tram"
                       }
                   },
                   {
                       "geometry_type": "Point",
                       "data_layer": "transit_stop_label",
                       "data_layer_fields": {
                           "mode": "bus"
                       }
                   },
                   {
                       "geometry_type": "Point",
                       "data_layer": "transit_stop_label",
                       "data_layer_fields": {
                           "mode": "bicycle"
                       }
                   }
               ]
           }
       }
   ]
}
